kx_publish_pypi/__init__.py
kx_publish_pypi/__version__.py
kx_publish_pypi/checks.py
kx_publish_pypi/cli.py
kx_publish_pypi/config.py
kx_publish_pypi/publish.py
kx_publish_pypi/pypi.py
kx_publish_pypi/report.py
kx_publish_pypi/test_pypi.py
kx_publish_pypi/utils.py
kx_publish_pypi/version_detection.py
kx_publish_pypi-1.0.3.dist-info/licenses/LICENSE
kx_publish_pypi-1.0.3.dist-info/METADATA
kx_publish_pypi-1.0.3.dist-info/WHEEL
kx_publish_pypi-1.0.3.dist-info/entry_points.txt
kx_publish_pypi-1.0.3.dist-info/top_level.txt
kx_publish_pypi-1.0.3.dist-info/RECORD
