Metadata-Version: 2.4
Name: kx_publish_pypi
Version: 1.0.3
Summary: A friendly CLI tool to check and publish Python packages to TestPyPI/PyPI
Author-email: ABUELTAYEF Khader <abueltayef.khader@gmail.com>
Maintainer-email: ABUELTAYEF Khader <abueltayef.khader.main@hotmail.com>
License-Expression: MIT
Project-URL: Homepage, https://github.com/Khader-X/kx-publish-pypi
Project-URL: Repository, https://github.com/Khader-X/kx-publish-pypi
Project-URL: Bug Tracker, https://github.com/Khader-X/kx-publish-pypi/issues
Project-URL: Website, https://KhaderX.com/
Project-URL: Organization, https://github.com/Khader-X
Project-URL: Author, https://github.com/KhaderX-com
Project-URL: PyPI, https://pypi.org/user/KhaderX/
Project-URL: Blog, https://khaderabueltayef.blogspot.com/
Project-URL: Gravatar, https://gravatar.com/voiddevotedlyf473f5471f
Keywords: publish,cli,pypi,packaging,release,kx
Classifier: Programming Language :: Python :: 3
Classifier: Programming Language :: Python :: 3.9
Classifier: Operating System :: OS Independent
Classifier: Environment :: Console
Classifier: Intended Audience :: Developers
Classifier: Topic :: Software Development :: Build Tools
Requires-Python: >=3.9
License-File: LICENSE
Requires-Dist: click>=8.1
Requires-Dist: rich>=13.0
Requires-Dist: tomli>=2.0; python_version < "3.11"
Requires-Dist: keyring>=24.0
Requires-Dist: twine>=4.0
Requires-Dist: build>=1.0
Dynamic: license-file
